oneiot_core/Parsers.py
oneiot_core/__init__.py
oneiot_core/__main__.py
oneiot_core/env.py
oneiot_core/iot-services.py
oneiot_core/main.py
oneiot_core/webrepl_cli.py
oneiot_core/websocket_helper.py
oneiot_core/tools/__init__.py
oneiot_core/tools/core.py
oneiot_core/tools/environment.py
oneiot_core/tools/network.py
oneiot_core/utils/EventBus.py
oneiot_core/utils/__init__.py
oneiot_core-0.1.7.data/scripts/iot-core
oneiot_core-0.1.7.data/scripts/iot-core-serve
oneiot_core-0.1.7.dist-info/METADATA
oneiot_core-0.1.7.dist-info/WHEEL
oneiot_core-0.1.7.dist-info/top_level.txt
oneiot_core-0.1.7.dist-info/RECORD
