Metadata-Version: 2.1
Name: oneiot-core
Version: 0.1.7
Summary: OneIoT Core
Home-page: https://github.com/lirwin3007/OneIoT-Core
Author: Louis Irwin
Author-email: coding@louisirwin.co.uk
License: UNKNOWN
Platform: UNKNOWN
Requires-Python: >=3.6
Requires-Dist: click
Requires-Dist: clint
Requires-Dist: netifaces
Requires-Dist: pystemd
Requires-Dist: websocket-client
Requires-Dist: websockets
